uri/__init__.py
uri/encoder.py
uri_encoder-0.0.0.dist-info/LICENSE
uri_encoder-0.0.0.dist-info/METADATA
uri_encoder-0.0.0.dist-info/WHEEL
uri_encoder-0.0.0.dist-info/top_level.txt
uri_encoder-0.0.0.dist-info/RECORD
