Metadata-Version: 2.1
Name: uri-encoder
Version: 0.0.0
Summary: A uri component encoder/decoder
Home-page: https://github.com/tony-o/python-uri-encoder
Author: Tony O'Dell
Author-email: tony.odell+python@live.com
License: LICENSE
Platform: UNKNOWN
